{
 "Week": "2026-01-07",
 "LastWeek": "",
 "X": 0.10816483960415857,
 "Programs": [
  {
   "Program": "cmd/asm",
   "Version": "go1.25.5",
   "GoVersion": "go1.25.5",
   "GOOS": "linux",
   "GOARCH": "amd64",
   "Counters": {
    "asm/flag:D": 18,
    "asm/flag:I": 18,
    "asm/flag:gensymabis": 9,
    "asm/flag:o": 18,
    "asm/flag:p": 18,
    "asm/flag:trimpath": 18,
    "asm/invocations": 18
   },
   "Stacks": {}
  },
  {
   "Program": "cmd/cgo",
   "Version": "go1.25.5",
   "GoVersion": "go1.25.5",
   "GOOS": "linux",
   "GOARCH": "amd64",
   "Counters": {},
   "Stacks": {}
  },
  {
   "Program": "cmd/compile",
   "Version": "go1.25.5",
   "GoVersion": "go1.25.5",
   "GOOS": "linux",
   "GOARCH": "amd64",
   "Counters": {
    "compile/flag:asmhdr": 9,
    "compile/flag:buildid": 347,
    "compile/flag:c": 347,
    "compile/flag:complete": 336,
    "compile/flag:dwarf": 34,
    "compile/flag:goversion": 347,
    "compile/flag:importcfg": 347,
    "compile/flag:lang": 347,
    "compile/flag:nolocalimports": 347,
    "compile/flag:o": 347,
    "compile/flag:p": 347,
    "compile/flag:pack": 347,
    "compile/flag:std": 26,
    "compile/flag:symabis": 9,
    "compile/flag:trimpath": 347,
    "compile/invocations": 786
   },
   "Stacks": {}
  },
  {
   "Program": "cmd/go",
   "Version": "go1.25.5",
   "GoVersion": "go1.25.5",
   "GOOS": "linux",
   "GOARCH": "amd64",
   "Counters": {
    "go/build/flag:o": 4,
    "go/buildcache/hit": 114611,
    "go/buildcache/miss": 2837,
    "go/buildcache/stdlib-recompiled": 41,
    "go/env/flag:json": 139,
    "go/get/flag:d": 5,
    "go/get/flag:modfile": 5,
    "go/get/flag:u": 7,
    "go/goroot:usr-local-go": 2508,
    "go/invocations": 2509,
    "go/list/flag:compiled": 378,
    "go/list/flag:deps": 378,
    "go/list/flag:e": 906,
    "go/list/flag:export": 378,
    "go/list/flag:f": 914,
    "go/list/flag:find": 378,
    "go/list/flag:json": 446,
    "go/list/flag:m": 134,
    "go/list/flag:mod": 71,
    "go/list/flag:modfile": 5,
    "go/list/flag:overlay": 897,
    "go/list/flag:pgo": 378,
    "go/list/flag:test": 378,
    "go/mod-edit/flag:modfile": 5,
    "go/mod-edit/flag:require": 5,
    "go/mod-tidy/flag:modfile": 354,
    "go/mode:gopath": 462,
    "go/mode:module": 2045,
    "go/platform/host/linux/major-version:6": 2507,
    "go/platform/host/linux/version:6-17": 2507,
    "go/platform/target/goamd64:v1": 2507,
    "go/platform/target/goarch:amd64": 2507,
    "go/platform/target/goos:linux": 2507,
    "go/subcommand:build": 16,
    "go/subcommand:env": 361,
    "go/subcommand:get": 17,
    "go/subcommand:list": 1360,
    "go/subcommand:mod-edit": 5,
    "go/subcommand:mod-init": 3,
    "go/subcommand:mod-tidy": 354,
    "go/subcommand:run": 47,
    "go/subcommand:unknown": 1,
    "go/subcommand:version": 344
   },
   "Stacks": {}
  },
  {
   "Program": "golang.org/x/tools/gopls",
   "Version": "v0.21.0",
   "GoVersion": "go1.25.5",
   "GOOS": "linux",
   "GOARCH": "amd64",
   "Counters": {
    "gopls/client:neovim": 78,
    "gopls/completion/latency:\u003c100ms": 9,
    "gopls/completion/latency:\u003c10ms": 692,
    "gopls/completion/latency:\u003c200ms": 140,
    "gopls/completion/latency:\u003c500ms": 1,
    "gopls/completion/latency:\u003c50ms": 221,
    "gopls/completion/len:0": 615,
    "gopls/completion/len:\u003c=10": 347,
    "gopls/completion/len:\u003e10": 101,
    "gopls/completion/used:no": 539,
    "gopls/definition/latency:\u003c10ms": 5,
    "gopls/gotoolchain:auto": 81,
    "gopls/goversion:1.25": 66,
    "gopls/setting/analyses/unusedparams:true": 189,
    "gopls/setting/completeUnimported:true": 189,
    "gopls/setting/usePlaceholders:true": 189,
    "gopls/telemetryprompt/attempts:0": 78
   },
   "Stacks": {}
  },
  {
   "Program": "cmd/link",
   "Version": "go1.25.5",
   "GoVersion": "go1.25.5",
   "GOOS": "linux",
   "GOARCH": "amd64",
   "Counters": {
    "link/flag:buildid": 48,
    "link/flag:buildmode": 48,
    "link/flag:extld": 48,
    "link/flag:importcfg": 48,
    "link/flag:o": 48,
    "link/flag:s": 34,
    "link/flag:w": 34,
    "link/invocations": 259
   },
   "Stacks": {}
  }
 ],
 "Config": "v0.0.0-0"
}